kvfile/VERSION
kvfile/__init__.py
kvfile/base.py
kvfile/cached.py
kvfile/kvfile.py
kvfile/kvfile_leveldb.py
kvfile/kvfile_sqlite.py
kvfile/serializer.py
kvfile/serializer_base.py
kvfile/serializer_json.py
kvfile/serializer_pickle.py
kvfile-1.1.2.dist-info/LICENSE.md
kvfile-1.1.2.dist-info/METADATA
kvfile-1.1.2.dist-info/WHEEL
kvfile-1.1.2.dist-info/top_level.txt
kvfile-1.1.2.dist-info/RECORD
