Metadata-Version: 2.1
Name: kvfile
Version: 1.1.2
Summary: Simple File-based KV-Store
Home-page: https://github.com/akariv/kvstore
Author: Adam Kariv
Author-email: adam.kariv@gmail.com
License: MIT
Keywords: data
Classifier: Development Status :: 4 - Beta
Classifier: Intended Audience :: Developers
Classifier: License :: OSI Approved :: MIT License
Classifier: Operating System :: OS Independent
Classifier: Programming Language :: Python :: 3.6
Classifier: Topic :: Software Development :: Libraries :: Python Modules
License-File: LICENSE.md
Requires-Dist: isodate
Requires-Dist: cachetools
Provides-Extra: develop
Requires-Dist: pylama; extra == "develop"
Requires-Dist: tox; extra == "develop"
Provides-Extra: speedup
Requires-Dist: plyvel; extra == "speedup"
